fw_client/__init__.py
fw_client/client.py
fw_client/errors.py
fw_client/py.typed
fw_client-2.1.4.dist-info/METADATA
fw_client-2.1.4.dist-info/WHEEL
fw_client-2.1.4.dist-info/licenses/LICENSE
fw_client-2.1.4.dist-info/RECORD
