Metadata-Version: 2.4
Name: fw-client
Version: 2.1.4
Summary: Flywheel HTTP API client.
Project-URL: Repository, https://gitlab.com/flywheel-io/tools/lib/fw-client
Project-URL: Documentation, https://gitlab.com/flywheel-io/tools/lib/fw-client
Author-email: Flywheel <support@flywheel.io>
License-Expression: MIT
License-File: LICENSE
Keywords: API,Flywheel,HTTP,client
Classifier: Topic :: Software Development :: Libraries :: Python Modules
Requires-Python: >=3.10
Requires-Dist: backoff<3,>=2.2.1
Requires-Dist: fw-utils<6,>=5.0.3
Requires-Dist: httpx[http2]<1,>=0
Requires-Dist: packaging>=23
